demo_transitive_dep_lol.py
demo_transitive_dep_lol-0.0.6.dist-info/LICENSE
demo_transitive_dep_lol-0.0.6.dist-info/WHEEL
demo_transitive_dep_lol-0.0.6.dist-info/METADATA
demo_transitive_dep_lol-0.0.6.dist-info/RECORD
