Metadata-Version: 2.1
Name: demo_transitive_dep_lol
Version: 0.0.6
Summary: a dependency used by another package...
Author-email: sohail-unity <sohail.khan@unity3d.com>
Classifier: License :: OSI Approved :: MIT License
